[{"content": "s", "sender": "Tom", "timestamp": "2025-02-19T16:47:01.406Z", "extra": null}, {"content": "s", "sender": "Tom", "timestamp": "2025-02-19T16:47:01.584Z", "extra": null}, {"content": "s", "sender": "Tom", "timestamp": "2025-02-19T16:47:01.765Z", "extra": null}, {"content": "s", "sender": "Tom", "timestamp": "2025-02-19T16:47:01.943Z", "extra": null}, {"content": "s", "sender": "Tom", "timestamp": "2025-02-19T16:47:02.137Z", "extra": null}, {"content": "s", "sender": "Tom", "timestamp": "2025-02-19T16:47:02.337Z", "extra": null}, {"content": "s", "sender": "Tom", "timestamp": "2025-02-19T16:47:02.518Z", "extra": null}, {"content": "s", "sender": "Tom", "timestamp": "2025-02-19T16:47:02.708Z", "extra": null}, {"content": "s", "sender": "Tom", "timestamp": "2025-02-19T16:47:02.890Z", "extra": null}, {"content": "s", "sender": "Tom", "timestamp": "2025-02-19T16:47:03.078Z", "extra": null}, {"content": "s", "sender": "Tom", "timestamp": "2025-02-19T16:47:03.249Z", "extra": null}, {"content": "s", "sender": "Tom", "timestamp": "2025-02-19T16:47:03.437Z", "extra": null}, {"content": "s", "sender": "Tom", "timestamp": "2025-02-19T16:47:03.611Z", "extra": null}, {"content": "s", "sender": "Tom", "timestamp": "2025-02-19T16:47:03.788Z", "extra": null}, {"content": "s", "sender": "Tom", "timestamp": "2025-02-19T16:47:03.982Z", "extra": null}, {"content": "s", "sender": "Tom", "timestamp": "2025-02-19T16:47:04.160Z", "extra": null}, {"content": "s", "sender": "Tom", "timestamp": "2025-02-19T16:47:04.351Z", "extra": null}, {"content": "s", "sender": "Tom", "timestamp": "2025-02-19T16:47:04.552Z", "extra": null}, {"content": "s", "sender": "Tom", "timestamp": "2025-02-19T16:47:04.767Z", "extra": null}, {"content": "s", "sender": "Tom", "timestamp": "2025-02-19T16:47:04.947Z", "extra": null}, {"content": "s", "sender": "Tom", "timestamp": "2025-02-19T16:47:05.136Z", "extra": null}, {"content": "s", "sender": "Tom", "timestamp": "2025-02-19T16:47:05.330Z", "extra": null}, {"content": "s", "sender": "Tom", "timestamp": "2025-02-19T16:47:05.520Z", "extra": null}, {"content": "s", "sender": "Tom", "timestamp": "2025-02-19T16:47:05.723Z", "extra": null}, {"content": "s", "sender": "Tom", "timestamp": "2025-02-19T16:47:05.904Z", "extra": null}, {"content": "s", "sender": "Tom", "timestamp": "2025-02-19T16:47:06.093Z", "extra": null}, {"content": "s", "sender": "Tom", "timestamp": "2025-02-19T16:47:06.294Z", "extra": null}, {"content": "s", "sender": "Tom", "timestamp": "2025-02-19T16:47:06.474Z", "extra": null}, {"content": "s", "sender": "Tom", "timestamp": "2025-02-19T16:47:06.688Z", "extra": null}, {"content": "s", "sender": "Tom", "timestamp": "2025-02-19T16:47:06.906Z", "extra": null}, {"content": "s", "sender": "Tom", "timestamp": "2025-02-19T16:47:07.107Z", "extra": null}, {"content": "s", "sender": "Tom", "timestamp": "2025-02-19T16:47:07.310Z", "extra": null}, {"content": "s", "sender": "Tom", "timestamp": "2025-02-19T16:47:07.513Z", "extra": null}, {"content": "s", "sender": "Tom", "timestamp": "2025-02-19T16:47:07.713Z", "extra": null}, {"content": "s", "sender": "Tom", "timestamp": "2025-02-19T16:47:07.916Z", "extra": null}, {"content": "s", "sender": "Tom", "timestamp": "2025-02-19T16:47:08.099Z", "extra": null}, {"content": "s", "sender": "Tom", "timestamp": "2025-02-19T16:47:08.287Z", "extra": null}, {"content": "s", "sender": "Tom", "timestamp": "2025-02-19T16:47:08.480Z", "extra": null}, {"content": "s", "sender": "Tom", "timestamp": "2025-02-19T16:47:08.668Z", "extra": null}, {"content": "s", "sender": "Tom", "timestamp": "2025-02-19T16:47:08.840Z", "extra": null}, {"content": "s", "sender": "Tom", "timestamp": "2025-02-19T16:47:09.029Z", "extra": null}, {"content": "s", "sender": "Tom", "timestamp": "2025-02-19T16:47:09.212Z", "extra": null}, {"content": "s", "sender": "Tom", "timestamp": "2025-02-19T16:47:09.414Z", "extra": null}, {"content": "s", "sender": "Tom", "timestamp": "2025-02-19T16:47:09.605Z", "extra": null}, {"content": "s", "sender": "Tom", "timestamp": "2025-02-19T16:47:09.797Z", "extra": null}, {"content": "s", "sender": "Tom", "timestamp": "2025-02-19T16:47:09.999Z", "extra": null}, {"content": "s", "sender": "Tom", "timestamp": "2025-02-19T16:47:10.190Z", "extra": null}, {"content": "s", "sender": "Tom", "timestamp": "2025-02-19T16:47:10.392Z", "extra": null}, {"content": "s", "sender": "Tom", "timestamp": "2025-02-19T16:47:10.594Z", "extra": null}, {"content": "s", "sender": "Tom", "timestamp": "2025-02-19T16:47:10.865Z", "extra": null}]